{
  "nodes": [
    {
      "id": "0",
      "type": "io",
      "position": {
        "x": 636,
        "y": 145.5
      },
      "data": {
        "descriptionFile": "ClimateMetrics>climateVelocity.yml"
      }
    },
    {
      "id": "1",
      "type": "constant",
      "position": {
        "x": 423,
        "y": 0
      },
      "dragHandle": ".dragHandle",
      "data": {
        "type": "options",
        "value": "local",
        "options": [
          "local",
          "forward",
          "backward"
        ]
      }
    },
    {
      "id": "2",
      "type": "constant",
      "position": {
        "x": 437,
        "y": 38
      },
      "dragHandle": ".dragHandle",
      "data": {
        "type": "options",
        "value": "ssp126",
        "options": [
          "ssp126",
          "ssp370",
          "ssp585"
        ]
      }
    },
    {
      "id": "3",
      "type": "constant",
      "position": {
        "x": 369,
        "y": 76
      },
      "dragHandle": ".dragHandle",
      "data": {
        "type": "int",
        "value": 1000
      }
    },
    {
      "id": "4",
      "type": "constant",
      "position": {
        "x": 361,
        "y": 116
      },
      "dragHandle": ".dragHandle",
      "data": {
        "type": "text",
        "value": "EPSG:6623"
      }
    },
    {
      "id": "5",
      "type": "constant",
      "position": {
        "x": 436,
        "y": 156
      },
      "dragHandle": ".dragHandle",
      "data": {
        "type": "options",
        "value": "mean",
        "options": [
          "min",
          "max",
          "mean",
          "median",
          "first"
        ]
      }
    },
    {
      "id": "6",
      "type": "constant",
      "position": {
        "x": 361,
        "y": 194
      },
      "dragHandle": ".dragHandle",
      "data": {
        "type": "text",
        "value": "1981-01-01"
      }
    },
    {
      "id": "7",
      "type": "constant",
      "position": {
        "x": 361,
        "y": 234
      },
      "dragHandle": ".dragHandle",
      "data": {
        "type": "text",
        "value": "1991-12-31"
      }
    },
    {
      "id": "8",
      "type": "constant",
      "position": {
        "x": 416,
        "y": 274
      },
      "dragHandle": ".dragHandle",
      "data": {
        "type": "options",
        "value": "2041-2070",
        "options": [
          "2011-2040",
          "2041-2070",
          "2071-2100"
        ]
      }
    },
    {
      "id": "10",
      "type": "io",
      "position": {
        "x": 382.5,
        "y": 312
      },
      "data": {
        "descriptionFile": "extent>shpToBbox.yml"
      }
    },
    {
      "id": "11",
      "type": "constant",
      "position": {
        "x": 0,
        "y": 320.5
      },
      "dragHandle": ".dragHandle",
      "data": {
        "type": "application/dbf",
        "value": "/scripts/extent/Quebec.shp"
      }
    },
    {
      "id": "12",
      "type": "constant",
      "position": {
        "x": 369,
        "y": 407
      },
      "dragHandle": ".dragHandle",
      "data": {
        "type": "int",
        "value": "0"
      }
    },
    {
      "id": "13",
      "type": "constant",
      "position": {
        "x": 369,
        "y": 447
      },
      "dragHandle": ".dragHandle",
      "data": {
        "type": "int",
        "value": 11
      }
    },
    {
      "id": "14",
      "type": "constant",
      "position": {
        "x": 356,
        "y": 487
      },
      "dragHandle": ".dragHandle",
      "data": {
        "type": "float",
        "value": 0.25
      }
    },
    {
      "id": "16",
      "type": "output",
      "position": {
        "x": 1015,
        "y": 229
      },
      "data": {
        "label": "Output"
      }
    },
    {
      "id": "17",
      "type": "constant",
      "position": {
        "x": 437,
        "y": 369
      },
      "dragHandle": ".dragHandle",
      "data": {
        "type": "options",
        "value": "bilinear",
        "options": [
          "bilinear",
          "near",
          "bicubic"
        ]
      }
    }
  ],
  "edges": [
    {
      "source": "1",
      "sourceHandle": null,
      "target": "0",
      "targetHandle": "metric",
      "id": "reactflow__edge-1-0metric"
    },
    {
      "source": "11",
      "sourceHandle": null,
      "target": "10",
      "targetHandle": "extent",
      "id": "reactflow__edge-11-10extent"
    },
    {
      "source": "0",
      "sourceHandle": "output_tif",
      "target": "16",
      "targetHandle": null,
      "id": "reactflow__edge-0output_tif-16"
    },
    {
      "source": "2",
      "sourceHandle": null,
      "target": "0",
      "targetHandle": "rcp",
      "id": "reactflow__edge-2-0rcp"
    },
    {
      "source": "3",
      "sourceHandle": null,
      "target": "0",
      "targetHandle": "spatial_res",
      "id": "reactflow__edge-3-0spatial_res"
    },
    {
      "source": "4",
      "sourceHandle": null,
      "target": "0",
      "targetHandle": "srs_cube",
      "id": "reactflow__edge-4-0srs_cube"
    },
    {
      "source": "5",
      "sourceHandle": null,
      "target": "0",
      "targetHandle": "aggregation",
      "id": "reactflow__edge-5-0aggregation"
    },
    {
      "source": "6",
      "sourceHandle": null,
      "target": "0",
      "targetHandle": "t0",
      "id": "reactflow__edge-6-0t0"
    },
    {
      "source": "7",
      "sourceHandle": null,
      "target": "0",
      "targetHandle": "t1",
      "id": "reactflow__edge-7-0t1"
    },
    {
      "source": "8",
      "sourceHandle": null,
      "target": "0",
      "targetHandle": "time_span",
      "id": "reactflow__edge-8-0time_span"
    },
    {
      "source": "10",
      "sourceHandle": "bbox",
      "target": "0",
      "targetHandle": "bbox",
      "id": "reactflow__edge-10bbox-0bbox"
    },
    {
      "source": "17",
      "sourceHandle": null,
      "target": "0",
      "targetHandle": "resampling",
      "id": "reactflow__edge-17-0resampling"
    },
    {
      "source": "12",
      "sourceHandle": null,
      "target": "0",
      "targetHandle": "buffer_box",
      "id": "reactflow__edge-12-0buffer_box"
    },
    {
      "source": "13",
      "sourceHandle": null,
      "target": "0",
      "targetHandle": "moving_window",
      "id": "reactflow__edge-13-0moving_window"
    },
    {
      "source": "14",
      "sourceHandle": null,
      "target": "0",
      "targetHandle": "t_match",
      "id": "reactflow__edge-14-0t_match"
    }
  ],
  "viewport": {
    "x": 0,
    "y": 0,
    "zoom": 1
  },
  "inputs": {}
}