{
  "nodes": [
    {
      "id": "0",
      "type": "io",
      "position": {
        "x": 679,
        "y": 129.16666666666669
      },
      "data": {
        "descriptionFile": "LAI>summariseLAI.yml"
      }
    },
    {
      "id": "1",
      "type": "io",
      "position": {
        "x": 1385,
        "y": 209.5
      },
      "data": {
        "descriptionFile": "SDM>SDM_maxEnt.json"
      }
    },
    {
      "id": "2",
      "type": "output",
      "position": {
        "x": 2122,
        "y": 12
      },
      "data": {
        "label": "Output"
      }
    },
    {
      "id": "4",
      "type": "output",
      "position": {
        "x": 2122,
        "y": 82
      },
      "data": {
        "label": "Output"
      }
    },
    {
      "id": "5",
      "type": "output",
      "position": {
        "x": 2122,
        "y": 47
      },
      "data": {
        "label": "Output"
      }
    },
    {
      "id": "6",
      "type": "output",
      "position": {
        "x": 2122,
        "y": 187
      },
      "data": {
        "label": "Output"
      }
    },
    {
      "id": "7",
      "type": "output",
      "position": {
        "x": 2122,
        "y": 117
      },
      "data": {
        "label": "Output"
      }
    },
    {
      "id": "8",
      "type": "output",
      "position": {
        "x": 2122,
        "y": 152
      },
      "data": {
        "label": "Output"
      }
    },
    {
      "id": "9",
      "type": "constant",
      "position": {
        "x": 267,
        "y": 192.5
      },
      "dragHandle": ".dragHandle",
      "data": {
        "type": "bboxCRS"
      }
    },
    {
      "id": "10",
      "type": "constant",
      "position": {
        "x": 12,
        "y": 86.16666666666667
      },
      "dragHandle": ".dragHandle",
      "data": {
        "type": "application/geopackage+sqlite3"
      }
    },
    {
      "id": "11",
      "type": "constant",
      "position": {
        "x": 302,
        "y": 142.5
      },
      "dragHandle": ".dragHandle",
      "data": {
        "type": "text",
        "value": "2024"
      }
    },
    {
      "id": "12",
      "type": "constant",
      "position": {
        "x": 302,
        "y": 277.5
      },
      "dragHandle": ".dragHandle",
      "data": {
        "type": "text",
        "value": "2017"
      }
    },
    {
      "id": "13",
      "type": "constant",
      "position": {
        "x": 239,
        "y": 327.5
      },
      "dragHandle": ".dragHandle",
      "data": {
        "type": "float",
        "value": 1000
      }
    }
  ],
  "edges": [
    {
      "source": "1",
      "sourceHandle": "filtering>cleanCoordinates.yml@34|clean_presence",
      "target": "2",
      "id": "xy-edge__1filtering>cleanCoordinates.yml@34|clean_presence-2"
    },
    {
      "source": "1",
      "sourceHandle": "pipeline@121|default_output",
      "target": "4",
      "id": "xy-edge__1pipeline@121|default_output-4"
    },
    {
      "source": "1",
      "sourceHandle": "SDM>removeCollinearity.yml@97|rasters_selected",
      "target": "5",
      "id": "xy-edge__1SDM>removeCollinearity.yml@97|rasters_selected-5"
    },
    {
      "source": "1",
      "sourceHandle": "SDM>rangePredictions.yml@68|range_predictions",
      "target": "6",
      "id": "xy-edge__1SDM>rangePredictions.yml@68|range_predictions-6"
    },
    {
      "source": "1",
      "sourceHandle": "SDM>runMaxent.yml@108|sdm_pred",
      "target": "7",
      "id": "xy-edge__1SDM>runMaxent.yml@108|sdm_pred-7"
    },
    {
      "source": "1",
      "sourceHandle": "data>getGBIFObservations>getGBIFObservations.yml@142|gbif_doi",
      "target": "8",
      "id": "xy-edge__1data>getGBIFObservations>getGBIFObservations.yml@142|gbif_doi-8"
    },
    {
      "source": "9",
      "target": "0",
      "targetHandle": "bbox_crs",
      "id": "xy-edge__9-0bbox_crs"
    },
    {
      "source": "9",
      "target": "1",
      "targetHandle": "pipeline@140",
      "id": "xy-edge__9-1pipeline@140"
    },
    {
      "source": "10",
      "target": "0",
      "targetHandle": "study_area_polygon",
      "id": "xy-edge__10-0study_area_polygon"
    },
    {
      "source": "10",
      "target": "1",
      "targetHandle": "data>loadFromStac.yml@144|study_area",
      "id": "xy-edge__10-1data>loadFromStac.yml@144|study_area"
    },
    {
      "source": "11",
      "target": "0",
      "targetHandle": "end_year",
      "id": "xy-edge__11-0end_year"
    },
    {
      "source": "11",
      "target": "1",
      "targetHandle": "data>loadFromStac.yml@144|t1",
      "id": "xy-edge__11-1data>loadFromStac.yml@144|t1"
    },
    {
      "source": "12",
      "target": "0",
      "targetHandle": "start_year",
      "id": "xy-edge__12-0start_year"
    },
    {
      "source": "12",
      "target": "1",
      "targetHandle": "data>loadFromStac.yml@144|t0",
      "id": "xy-edge__12-1data>loadFromStac.yml@144|t0"
    },
    {
      "source": "13",
      "target": "0",
      "targetHandle": "spatial_resolution",
      "id": "xy-edge__13-0spatial_resolution"
    },
    {
      "source": "13",
      "target": "1",
      "targetHandle": "pipeline@128",
      "id": "xy-edge__13-1pipeline@128"
    },
    {
      "source": "0",
      "sourceHandle": "rasters",
      "target": "1",
      "targetHandle": "data>loadFromStac.yml@144|collections_items",
      "id": "xy-edge__0rasters-1data>loadFromStac.yml@144|collections_items"
    }
  ],
  "inputs": {
    "SDM>SDM_maxEnt.json@1|pipeline@121": {
      "description": "Array of taxa",
      "label": "Taxa list",
      "type": "text[]",
      "example": [
        "Acer saccharum"
      ],
      "weight": 0
    },
    "SDM>SDM_maxEnt.json@1|data>getGBIFObservations>getGBIFObservations.yml@142|max_year": {
      "description": "Max year observations wanted",
      "label": "Maximum year",
      "type": "int",
      "example": 2024,
      "weight": 1
    },
    "SDM>SDM_maxEnt.json@1|SDM>selectBackground.yml@40|method_background": {
      "description": "method used to sample background points",
      "label": "Method background",
      "type": "options",
      "options": [
        "random",
        "inclusion_buffer",
        "weighted_raster",
        "unweighted_raster"
      ],
      "example": "random",
      "weight": 2
    },
    "SDM>SDM_maxEnt.json@1|data>GBIFHeatmapFromSTAC.yml@139|taxa": {
      "description": "taxonomic group of the taxa from the taxa list, for which to retrieve GBIF heatmap",
      "label": "Taxa",
      "type": "options",
      "options": [
        "reptiles",
        "plants",
        "mammals",
        "birds",
        "arthropods",
        "amphibians",
        "all"
      ],
      "example": "plants",
      "weight": 3
    },
    "SDM>SDM_maxEnt.json@1|SDM>runMaxent.yml@108|partition_type": {
      "description": "String, name of partitioning technique.",
      "label": "Partition type",
      "type": "options",
      "options": [
        "randomkfold",
        "jackknife",
        "block",
        "checkerboard1",
        "checkerboard2"
      ],
      "example": "block",
      "weight": 4
    },
    "SDM>SDM_maxEnt.json@1|data>loadFromStac.yml@144|temporal_res": {
      "description": "Temporal resolution to use when querying STAC items by date, in the format (\"P\", time interval, and time unit, e.g. \"P1Y\" is yearly, \"P1M\" is montly, and \"P1D\" is daily). Leave blank if not querying by date. If the temporal resolution is coarser than the temporal resolution of the time series, the layers will be aggregated with the aggregation method chosen below.",
      "label": "Temporal resolution",
      "type": "text",
      "example": null,
      "weight": 5
    },
    "SDM>SDM_maxEnt.json@1|SDM>selectBackground.yml@40|n_background": {
      "description": "number of background points",
      "label": "Number of background points",
      "type": "int",
      "example": 10000,
      "weight": 6
    },
    "SDM>SDM_maxEnt.json@1|data>loadFromStac.yml@144|stac_url": {
      "description": "URL of the STAC catalog.",
      "label": "STAC URL",
      "type": "text",
      "example": "https://stac.geobon.org/",
      "weight": 7
    },
    "SDM>SDM_maxEnt.json@1|data>getGBIFObservations>getGBIFObservations.yml@142|min_year": {
      "description": "Min year observations wanted",
      "label": "Minimum year",
      "type": "int",
      "example": 2010,
      "weight": 8
    },
    "SDM>SDM_maxEnt.json@1|pipeline@46": {
      "description": "number of runs (in bootstrap or crossvalidation method)",
      "label": "Number of runs",
      "type": "int",
      "example": 2,
      "weight": 9
    }
  },
  "outputs": {
    "SDM>SDM_maxEnt.json@1|filtering>cleanCoordinates.yml@34|clean_presence": {
      "description": "Occurrences from GBIF after cleaning",
      "label": "Presences",
      "type": "text/tab-separated-values",
      "weight": 0
    },
    "SDM>SDM_maxEnt.json@1|pipeline@121|default_output": {
      "description": "Species for which this model was run.",
      "label": "Species",
      "type": "text[]",
      "example": [
        "Acer saccharum"
      ],
      "weight": 1
    },
    "SDM>SDM_maxEnt.json@1|SDM>removeCollinearity.yml@97|rasters_selected": {
      "description": "Environmental layers used as predictors in species distribution modeling",
      "label": "Environmental predictors",
      "type": "image/tiff;application=geotiff[]",
      "weight": 2
    },
    "SDM>SDM_maxEnt.json@1|SDM>rangePredictions.yml@68|range_predictions": {
      "description": "Variability of predictions based on range method",
      "label": "Variability of predictions",
      "type": "image/tiff;application=geotiff",
      "weight": 3
    },
    "SDM>SDM_maxEnt.json@1|SDM>runMaxent.yml@108|sdm_pred": {
      "description": "Model predictions from Maxent algorithm",
      "label": "Predictions",
      "type": "image/tiff;application=geotiff",
      "range": [
        0,
        1
      ],
      "weight": 4
    },
    "SDM>SDM_maxEnt.json@1|data>getGBIFObservations>getGBIFObservations.yml@142|gbif_doi": {
      "description": "DOI of GBIF download. Used for citing downloaded data.",
      "label": "DOI of GBIF download",
      "type": "text",
      "example": "10.15468/dl.j644h5",
      "weight": 5
    }
  },
  "metadata": {
    "name": null,
    "description": null,
    "author": [
      {
        "name": null,
        "email": null,
        "identifier": null
      }
    ],
    "license": null,
    "external_link": null,
    "references": [
      {
        "text": null,
        "link": null
      },
      {
        "text": null,
        "link": null
      }
    ]
  }
}