{
  "nodes": [
    {
      "id": "10",
      "type": "io",
      "position": {
        "x": 62,
        "y": 32
      },
      "data": {
        "descriptionFile": "IUCN_redlist_spList>IUCN_redlist_spList.yml"
      }
    },
    {
      "id": "13",
      "type": "io",
      "position": {
        "x": 480,
        "y": 22
      },
      "data": {
        "descriptionFile": "IUCN_redlist_historyAssesment>IUCN_redlist_historyAssesment.yml"
      }
    },
    {
      "id": "14",
      "type": "constant",
      "position": {
        "x": 120,
        "y": 112
      },
      "dragHandle": ".dragHandle",
      "data": {
        "type": "text",
        "value": "scientific_name"
      }
    },
    {
      "id": "15",
      "type": "io",
      "position": {
        "x": 1087,
        "y": 113.33333333333333
      },
      "data": {
        "descriptionFile": "RedListIndex>RedListIndex.yml"
      }
    },
    {
      "id": "18",
      "type": "output",
      "position": {
        "x": 1578.908243849231,
        "y": 91.16148339439854
      },
      "data": {
        "label": "Output"
      }
    },
    {
      "id": "19",
      "type": "constant",
      "position": {
        "x": 717,
        "y": 144.33333333333331
      },
      "dragHandle": ".dragHandle",
      "data": {
        "type": "text",
        "value": "assess_year"
      }
    },
    {
      "id": "20",
      "type": "constant",
      "position": {
        "x": 717,
        "y": 186.33333333333331
      },
      "dragHandle": ".dragHandle",
      "data": {
        "type": "text",
        "value": "code"
      }
    },
    {
      "id": "21",
      "type": "output",
      "position": {
        "x": 1576.0163269042969,
        "y": 134.66665649414062
      },
      "data": {
        "label": "Output"
      }
    }
  ],
  "edges": [
    {
      "source": "10",
      "sourceHandle": "iucn_splist",
      "target": "13",
      "targetHandle": "species_data",
      "id": "reactflow__edge-10iucn_splist-13species_data"
    },
    {
      "source": "14",
      "sourceHandle": null,
      "target": "13",
      "targetHandle": "sp_col",
      "id": "reactflow__edge-14-13sp_col"
    },
    {
      "source": "13",
      "sourceHandle": "iucn_history_assessment_data",
      "target": "15",
      "targetHandle": "history_assessment_data",
      "id": "reactflow__edge-13iucn_history_assessment_data-15history_assessment_data"
    },
    {
      "source": "14",
      "sourceHandle": null,
      "target": "15",
      "targetHandle": "sp_col",
      "id": "reactflow__edge-14-15sp_col"
    },
    {
      "source": "15",
      "sourceHandle": "redlist_trend_plot",
      "target": "18",
      "targetHandle": null,
      "id": "reactflow__edge-15redlist_trend_plot-18"
    },
    {
      "source": "19",
      "sourceHandle": null,
      "target": "15",
      "targetHandle": "time_col",
      "id": "reactflow__edge-19-15time_col"
    },
    {
      "source": "20",
      "sourceHandle": null,
      "target": "15",
      "targetHandle": "threat_category_code_column",
      "id": "reactflow__edge-20-15threat_category_code_column"
    },
    {
      "source": "15",
      "sourceHandle": "redlist_data",
      "target": "21",
      "targetHandle": null,
      "id": "reactflow__edge-15redlist_data-21"
    }
  ],
  "inputs": {
    "IUCN_redlist_spList>IUCN_redlist_spList.yml@10|taxonomic_group": {
      "description": "Select the taxonomic group to obtain the list of species. If 'all' is selected, a list of all species listed by the IUCN for the selected country will be obtained.",
      "label": "Taxonomic group",
      "type": "options",
      "options": [
        "all",
        "amphibians",
        "birds",
        "mammals",
        "reptiles",
        "angelfishes",
        "blennies",
        "butterfly_fishes",
        "cacti",
        "chameleons",
        "cone_snails",
        "conifers",
        "crocodiles_and_alligators",
        "cycads",
        "fw_caridean_shrimps",
        "fw_crabs",
        "fw_crayfish",
        "hagfishes",
        "lobsters",
        "magnolias",
        "mangrove_plants",
        "pufferfishes",
        "reef_building_corals",
        "seabreams_porgies_picarels",
        "seagrasses",
        "seasnakes",
        "sharks_and_rays",
        "sturgeons",
        "surgeonfishes",
        "tarpons_and_ladyfishes",
        "tunas_and_billfishes",
        "wrasses_and_parrotfishes"
      ],
      "example": "mammals",
      "weight": 0
    },
    "IUCN_redlist_spList>IUCN_redlist_spList.yml@10|country": {
      "description": "Select the country to obtain the list of species.",
      "label": "country",
      "type": "options",
      "options": [
        "Colombia",
        "Canada",
        "Afghanistan",
        "Albania",
        "Algeria",
        "American Samoa",
        "Andorra",
        "Angola",
        "Anguilla",
        "Antarctica",
        "Antigua and Barbuda",
        "Argentina",
        "Armenia",
        "Aruba",
        "Australia",
        "Austria",
        "Azerbaijan",
        "Bahamas",
        "Bahrain",
        "Bangladesh",
        "Barbados",
        "Belarus",
        "Belgium",
        "Belize",
        "Benin",
        "Bermuda",
        "Bhutan",
        "Bolivia, Plurinational State of",
        "Bonaire, Sint Eustatius and Saba",
        "Bosnia and Herzegovina",
        "Botswana",
        "Bouvet Island",
        "Brazil",
        "British Indian Ocean Territory",
        "Brunei Darussalam",
        "Bulgaria",
        "Burkina Faso",
        "Burundi",
        "Cabo Verde",
        "Cambodia",
        "Cameroon",
        "Cayman Islands",
        "Central African Republic",
        "Chad",
        "Chile",
        "China",
        "Christmas Island",
        "Cocos (Keeling) Islands",
        "Comoros",
        "Congo",
        "Congo, The Democratic Republic of the",
        "Cook Islands",
        "Costa Rica",
        "Croatia",
        "Cuba",
        "Curaçao",
        "Cyprus",
        "Czechia",
        "Côte d'Ivoire",
        "Denmark",
        "Djibouti",
        "Dominica",
        "Dominican Republic",
        "Ecuador",
        "Egypt",
        "El Salvador",
        "Equatorial Guinea",
        "Eritrea",
        "Estonia",
        "Eswatini",
        "Ethiopia",
        "Falkland Islands (Malvinas)",
        "Faroe Islands",
        "Fiji",
        "Finland",
        "France",
        "French Guiana",
        "French Polynesia",
        "French Southern Territories",
        "Gabon",
        "Gambia",
        "Georgia",
        "Germany",
        "Ghana",
        "Gibraltar",
        "Greece",
        "Greenland",
        "Grenada",
        "Guadeloupe",
        "Guam",
        "Guatemala",
        "Guernsey",
        "Guinea",
        "Guinea-Bissau",
        "Guyana",
        "Haiti",
        "Heard Island and McDonald Islands",
        "Holy See (Vatican City State)",
        "Honduras",
        "Hong Kong",
        "Hungary",
        "Iceland",
        "India",
        "Indonesia",
        "Iran, Islamic Republic of",
        "Iraq",
        "Ireland",
        "Israel",
        "Italy",
        "Jamaica",
        "Japan",
        "Jersey",
        "Jordan",
        "Kazakhstan",
        "Kenya",
        "Kiribati",
        "Korea, Democratic People's Republic of",
        "Korea, Republic of",
        "Kuwait",
        "Kyrgyzstan",
        "Lao People's Democratic Republic",
        "Latvia",
        "Lebanon",
        "Lesotho",
        "Liberia",
        "Libya",
        "Liechtenstein",
        "Lithuania",
        "Luxembourg",
        "Macao",
        "Madagascar",
        "Malawi",
        "Malaysia",
        "Maldives",
        "Mali",
        "Malta",
        "Marshall Islands",
        "Martinique",
        "Mauritania",
        "Mauritius",
        "Mayotte",
        "Mexico",
        "Micronesia, Federated States of",
        "Moldova, Republic of",
        "Monaco",
        "Mongolia",
        "Montenegro",
        "Montserrat",
        "Morocco",
        "Mozambique",
        "Myanmar",
        "Namibia",
        "Nauru",
        "Nepal",
        "Netherlands",
        "Netherlands Antilles",
        "New Caledonia",
        "New Zealand",
        "Nicaragua",
        "Niger",
        "Nigeria",
        "Niue",
        "Norfolk Island",
        "North Macedonia",
        "Northern Mariana Islands",
        "Norway",
        "Oman",
        "Pakistan",
        "Palau",
        "Palestine, State of",
        "Panama",
        "Papua New Guinea",
        "Paraguay",
        "Peru",
        "Philippines",
        "Pitcairn",
        "Poland",
        "Portugal",
        "Puerto Rico",
        "Qatar",
        "Romania",
        "Russian Federation",
        "Rwanda",
        "Réunion",
        "Saint Barthélemy",
        "Saint Helena, Ascension and Tristan da Cunha",
        "Saint Kitts and Nevis",
        "Saint Lucia",
        "Saint Martin (French part)",
        "Saint Pierre and Miquelon",
        "Saint Vincent and the Grenadines",
        "Samoa",
        "San Marino",
        "Sao Tome and Principe",
        "Saudi Arabia",
        "Senegal",
        "Serbia",
        "Seychelles",
        "Sierra Leone",
        "Singapore",
        "Sint Maarten (Dutch part)",
        "Slovakia",
        "Slovenia",
        "Solomon Islands",
        "Somalia",
        "South Africa",
        "South Georgia and the South Sandwich Islands",
        "South Sudan",
        "Spain",
        "Sri Lanka",
        "Sudan",
        "Suriname",
        "Svalbard and Jan Mayen",
        "Sweden",
        "Switzerland",
        "Syrian Arab Republic",
        "Taiwan, Province of China",
        "Tajikistan",
        "Tanzania, United Republic of",
        "Thailand",
        "Timor-Leste",
        "Togo",
        "Tokelau",
        "Tonga",
        "Trinidad and Tobago",
        "Tunisia",
        "Turkey",
        "Turkmenistan",
        "Turks and Caicos Islands",
        "Tuvalu",
        "Uganda",
        "Ukraine",
        "United Arab Emirates",
        "United Kingdom of Great Britain and Northern Ireland",
        "United States Minor Outlying Islands",
        "United States of America",
        "Uruguay",
        "Uzbekistan",
        "Vanuatu",
        "Venezuela, Bolivarian Republic of",
        "Viet Nam",
        "Virgin Islands, British",
        "Virgin Islands, U.S.",
        "Wallis and Futuna",
        "Western Sahara",
        "Yemen",
        "Zambia",
        "Zimbabwe"
      ],
      "example": "Colombia",
      "weight": 1
    }
  },
  "outputs": {
    "RedListIndex>RedListIndex.yml@15|redlist_trend_plot": {
      "description": "Figure showing the trend of the Red List Index (RLI) for the evaluated group of species. For more information about the workflow and the interpretation of the results consult the documentation [RLI documentation](https://html-preview.github.io/?url=https://github.com/PEM-Humboldt/biab-2.0/blob/RLI_pipeline/pipelines/RLI_pipeline/IUCN_RLI_pipeline.html) ",
      "label": "redlist trend plot",
      "type": "image/jpg",
      "weight": 0
    },
    "RedListIndex>RedListIndex.yml@15|redlist_data": {
      "description": "Dataset containing the results of the Red List Index (RLI) calculation.",
      "label": "redList data",
      "type": "text/csv",
      "weight": 1
    }
  },
  "metadata": {
    "name": "Red List Index (RLI) pipeline",
    "description": "This pipeline calculates the \nRLI by filtering the IUCN data by country and taxonomic group.",
    "author": [
      {
        "name": "Victor Julio Rincon",
        "identifier": "rincon-v@javeriana.edu.co"
      },
      {
        "name": "Maria Camila Diaz",
        "identifier": "maria.camila.diaz.corzo@usherbrooke.ca"
      }
    ],
    "license": "MIT",
    "external_link":"https://html-preview.github.io/?url=https://github.com/PEM-Humboldt/biab-2.0/blob/RLI_pipeline/pipelines/RLI_pipeline/IUCN_RLI_pipeline.html" 
  }
}